my_own_package/__init__.py
mary_proiect_hello-0.2.0.dist-info/METADATA
mary_proiect_hello-0.2.0.dist-info/WHEEL
mary_proiect_hello-0.2.0.dist-info/top_level.txt
mary_proiect_hello-0.2.0.dist-info/RECORD
