Metadata-Version: 2.1
Name: mary-proiect-hello
Version: 0.2.0
Summary: says hello to owner
Home-page: UNKNOWN
Author: Maria Juganaru
Author-email: maryjuganaru@gmail.com
License: UNKNOWN
Platform: UNKNOWN
